mgtdisklib/Disk.py
mgtdisklib/File.py
mgtdisklib/Image.py
mgtdisklib/__init__.py
tests/__init__.py
tests/runtests.py
tests/test_disk.py
tests/test_file.py
tests/test_image.py
mgtdisklib-0.5.3.dist-info/License.txt
mgtdisklib-0.5.3.dist-info/METADATA
mgtdisklib-0.5.3.dist-info/WHEEL
mgtdisklib-0.5.3.dist-info/top_level.txt
mgtdisklib-0.5.3.dist-info/RECORD
