Metadata-Version: 2.1
Name: mgtdisklib
Version: 0.5.3
Summary: Disk manipulation for SAM Coupé and MGT +D disks images
Home-page: https://github.com/simonowen/mgtdisklib
Author: Simon Owen
Author-email: simon@simonowen.com
License: MIT
Keywords: mgt disk sam coupe
Platform: UNKNOWN
Classifier: Development Status :: 3 - Alpha
Classifier: Intended Audience :: Developers
Classifier: Topic :: System :: Emulators
Classifier: Programming Language :: Python :: 3.6
Classifier: License :: OSI Approved :: MIT License
Requires-Dist: bitarray
